causalty/__init__.py
causalty/erc.py
causalty/mvar.py
causalty/util.py
causalty-0.0.1.dist-info/LICENSE
causalty-0.0.1.dist-info/METADATA
causalty-0.0.1.dist-info/WHEEL
causalty-0.0.1.dist-info/top_level.txt
causalty-0.0.1.dist-info/RECORD
