Metadata-Version: 2.1
Name: causalty
Version: 0.0.1
Summary: Causality Analysis Tools for Neuroimaging Data
Home-page: https://github.com/bgalbraith/causalty
Author: Byron Galbraith
Author-email: byron.galbraith@gmail.com
License: UNKNOWN
Platform: UNKNOWN
Classifier: Development Status :: 3 - Alpha
Classifier: Intended Audience :: Science/Research
Classifier: License :: OSI Approved :: GNU General Public License v3 (GPLv3)
Classifier: Operating System :: OS Independent
Classifier: Programming Language :: Python :: 3.6
Classifier: Programming Language :: Python :: 3.7
Requires-Python: >=3.6
